README.md
pyproject.toml
setup.py
benu/__init__.py
benu/benu.py
benu/benu_colormaps.py
benu/utils.py
benu.egg-info/PKG-INFO
benu.egg-info/SOURCES.txt
benu.egg-info/dependency_links.txt
benu.egg-info/top_level.txt