Metadata-Version: 2.1
Name: benu
Version: 0.1.1
Summary: python plotting tool
Home-page: UNKNOWN
License: UNKNOWN
Platform: UNKNOWN
